{
  "Class": [
    {
      "Name": "Warrior",
      "Attack": 3,
      "Defense": 3,
      "HP": 10,
      "Movement": 8,
      "Special": "Multistrike"
    },
    {
      "Name": "Paladin",
      "Attack": 2,
      "Defense": 4,
      "HP": 12,
      "Movement": 6,
      "Special": "Protection"
    },
    {
      "Name": "Mage",
      "Attack": 4,
      "Defense": 2,
      "HP": 4,
      "Movement": 10,
      "Special": "Spells"
    },
    {
      "Name": "Thief",
      "Attack": 2,
      "Defense": 2,
      "HP": 6,
      "Movement": 10,
      "Special": "Thief"
    },
    {
      "Name": "Barbarian",
      "Attack": 5,
      "Defense": 2,
      "HP": 12,
      "Movement": 12,
      "Special": "Destructor"
    },
    {
      "Name": "Priest",
      "Attack": 2,
      "Defense": 3,
      "HP": 8,
      "Movement": 8,
      "Special": "Heal"
    },
    {
      "Name": "Monk",
      "Attack": 5,
      "Defense": 1,
      "HP": 6,
      "Movement": 10,
      "Special": "You don't know yet but you're already dead..."
    },
    {
      "Name": "Ninja",
      "Attack": 2,
      "Defense": 2,
      "HP": 6,
      "Movement": 10,
      "Special": "Ninja!"
    },
    {
      "Name": "Archer",
      "Attack": 4,
      "Defense": 2,
      "HP": 6,
      "Movement": 10,
      "Special": "Bow"
    }
  ]
}